brasil.gov.vcge-2.0.2-py2.7-nspkg.pth
brasil/gov/vcge/__init__.py
brasil/gov/vcge/config.py
brasil/gov/vcge/configure.zcml
brasil/gov/vcge/interfaces.py
brasil/gov/vcge/profiles.zcml
brasil/gov/vcge/testing.py
brasil/gov/vcge/utils.py
brasil/gov/vcge/vocabulary.py
brasil/gov/vcge/at/__init__.py
brasil/gov/vcge/at/configure.zcml
brasil/gov/vcge/at/extender.py
brasil/gov/vcge/at/profiles/default/metadata.xml
brasil/gov/vcge/browser/__init__.py
brasil/gov/vcge/browser/configure.zcml
brasil/gov/vcge/browser/viewlets.py
brasil/gov/vcge/browser/resources/ico-brasil.png
brasil/gov/vcge/browser/templates/vcge.pt
brasil/gov/vcge/browser/templates/vcge_head.pt
brasil/gov/vcge/contentrules/__init__.py
brasil/gov/vcge/contentrules/action.py
brasil/gov/vcge/contentrules/condition.py
brasil/gov/vcge/contentrules/configure.zcml
brasil/gov/vcge/contentrules/utils.py
brasil/gov/vcge/controlpanel/__init__.py
brasil/gov/vcge/controlpanel/configure.zcml
brasil/gov/vcge/data/vcge.n3
brasil/gov/vcge/dx/__init__.py
brasil/gov/vcge/dx/behaviors.py
brasil/gov/vcge/dx/configure.zcml
brasil/gov/vcge/dx/interfaces.py
brasil/gov/vcge/dx/skos_display.pt
brasil/gov/vcge/dx/skos_input.pt
brasil/gov/vcge/dx/widget.py
brasil/gov/vcge/dx/profiles/default/metadata.xml
brasil/gov/vcge/locales/brasil.gov.vcge-manual.pot
brasil/gov/vcge/locales/brasil.gov.vcge.pot
brasil/gov/vcge/locales/update.sh
brasil/gov/vcge/locales/pt_BR/LC_MESSAGES/brasil.gov.vcge.po
brasil/gov/vcge/profiles/default/brasil.gov.vcge-default.txt
brasil/gov/vcge/profiles/default/browserlayer.xml
brasil/gov/vcge/profiles/default/catalog.xml
brasil/gov/vcge/profiles/default/controlpanel.xml
brasil/gov/vcge/profiles/default/cssregistry.xml
brasil/gov/vcge/profiles/default/metadata.xml
brasil/gov/vcge/profiles/default/registry.xml
brasil/gov/vcge/profiles/default/viewlets.xml
brasil/gov/vcge/profiles/uninstall/brasil.gov.vcge-uninstall.txt
brasil/gov/vcge/tests/__init__.py
brasil.gov.vcge-2.0.2.dist-info/DESCRIPTION.rst
brasil.gov.vcge-2.0.2.dist-info/METADATA
brasil.gov.vcge-2.0.2.dist-info/RECORD
brasil.gov.vcge-2.0.2.dist-info/WHEEL
brasil.gov.vcge-2.0.2.dist-info/entry_points.txt
brasil.gov.vcge-2.0.2.dist-info/metadata.json
brasil.gov.vcge-2.0.2.dist-info/namespace_packages.txt
brasil.gov.vcge-2.0.2.dist-info/top_level.txt
