Metadata-Version: 2.0
Name: brasil.gov.vcge
Version: 2.0.2
Summary: .gov.br: VocabulĂĄrio Controlado do Governo EletrĂ´nico
Home-page: http://www.plone.org.br/gov/
Author: PloneGov.Br
Author-email: gov@plone.org.br
License: GPLv2
Keywords: brasil.gov.br vcge plone plonegovbr vocabularios
Platform: UNKNOWN
Classifier: Development Status :: 5 - Production/Stable
Classifier: Environment :: Web Environment
Classifier: Framework :: Plone
Classifier: Framework :: Plone :: 4.3
Classifier: Intended Audience :: Developers
Classifier: License :: OSI Approved :: GNU General Public License v2 (GPLv2)
Classifier: Operating System :: OS Independent
Classifier: Programming Language :: Python
Classifier: Programming Language :: Python :: 2.7
Classifier: Topic :: Internet :: WWW/HTTP
Classifier: Topic :: Internet :: WWW/HTTP :: Dynamic Content
Classifier: Topic :: Software Development :: Libraries :: Python Modules
Requires-Dist: future
Requires-Dist: Plone (>=4.3)
Requires-Dist: plone.api
Requires-Dist: raptus.autocompletewidget
Requires-Dist: rdflib
Requires-Dist: setuptools
Requires-Dist: zope.component
Requires-Dist: z3c.form
Requires-Dist: zope.interface
Provides-Extra: archetypes
Requires-Dist: archetypes.schemaextender; extra == 'archetypes'
Requires-Dist: Products.ATContentTypes; extra == 'archetypes'
Requires-Dist: Products.Archetypes; extra == 'archetypes'
Provides-Extra: develop
Requires-Dist: Sphinx; extra == 'develop'
Requires-Dist: manuel; extra == 'develop'
Requires-Dist: pep8; extra == 'develop'
Requires-Dist: setuptools-flakes; extra == 'develop'
Provides-Extra: dexterity
Requires-Dist: plone.app.dexterity[grok]; extra == 'dexterity'
Requires-Dist: plone.autoform; extra == 'dexterity'
Requires-Dist: plone.behavior; extra == 'dexterity'
Requires-Dist: plone.indexer; extra == 'dexterity'
Requires-Dist: Products.CMFPlone; extra == 'dexterity'
Provides-Extra: test
Requires-Dist: interlude; extra == 'test'
Requires-Dist: plone.app.testing; extra == 'test'
Requires-Dist: unittest2; extra == 'test'
